hanlingzhi/__init__.py
hanlingzhi/math_h.py
string_h/__init__.py
string_h/reverse.py
hanlingzhi_test-0.0.2.dist-info/LICENSE.txt
hanlingzhi_test-0.0.2.dist-info/METADATA
hanlingzhi_test-0.0.2.dist-info/WHEEL
hanlingzhi_test-0.0.2.dist-info/top_level.txt
hanlingzhi_test-0.0.2.dist-info/RECORD
