Metadata-Version: 2.1
Name: hanlingzhi-test
Version: 0.0.2
Summary: 验证打包功能的测试包, 请勿下载
Home-page: https://github.com/hanlingzhi/PackageToPypi-Demo
Author: Han LingZhi
Author-email: 343651570@qq.com
License: MIT
Keywords: hanlingzhi package demo
Platform: UNKNOWN
Classifier: Development Status :: 3 - Alpha
Classifier: Intended Audience :: Developers
Classifier: Topic :: Software Development :: Build Tools
Classifier: License :: OSI Approved :: MIT License
Classifier: Programming Language :: Python :: 3
Classifier: Programming Language :: Python :: 3.2
Classifier: Programming Language :: Python :: 3.3
Classifier: Programming Language :: Python :: 3.4
Classifier: Operating System :: OS Independent
Requires-Python: >=3.6
Requires-Dist: pytest
